{"inkVersion":21,"root":[["\n",["done",{"#f":5,"#n":"g-0"}],null],"done",{"virgin":["#","^color: ffae1e","/#","^NPC: Would you like to chat?","\n","^MC: You know you don't always have to ask like that?","\n","^NPC: Like what? I'm just trying to be considerate.","\n","end",{"#f":1}],"conspiracist":["^[...]","\n","^MC: ...and no matter what I do I just can't stop loving them. I thought that entangling would maybe distract or make me forget about them. But it doesn't. It just makes their absence wider.","\n","^Conspiracist: Wow, you're really fucking pathetic?","\n","^MC: Hey! What the hell?!","\n","^Conspiracist: What?","\n","^MC: That's.. really rude! I was opening up to you.","\n","^Conspiracist: I was just being honest. You sounded really pathetic.","\n","^MC: Stop saying that!","\n","^...","\n","^Conspiracist: It's not your fault that you're pathetic.","\n","^MC: ...","\n","^[...]","\n","end",{"#f":1}],"nextBrainKnot":["ev",{"x()":"nextBrain"},"pop","/ev","\n","end",{"#f":1}],"muffleNPCsVolume":["ev","str","^npcSingingVolume","/str",0.3,{"x()":"setFMODGlobalParameter","exArgs":2},"pop","/ev","\n",{"#f":1}],"restoreNPCsVolume":["ev","str","^npcSingingVolume","/str",1,{"x()":"setFMODGlobalParameter","exArgs":2},"pop","/ev","\n",{"#f":1}],"npcStart":["ev",{"x()":"stopSinging"},"pop","/ev","\n","ev",true,{"x()":"pauseTutorial","exArgs":1},"pop","/ev","\n","ev",{"f()":"muffleNPCsVolume"},"pop","/ev","\n","ev","str","^standard","/str",{"x()":"setDialogueBubble","exArgs":1},"pop","/ev","\n",["ev",{"VAR?":"world"},1,"==","/ev",{"->":".^.b","c":true},{"b":["\n","ev","str","^floral","/str",true,{"x()":"activateBorder","exArgs":2},"pop","/ev","\n",{"->":".^.^.^.26"},null]}],["ev",{"VAR?":"world"},2,"==","/ev",{"->":".^.b","c":true},{"b":["\n","ev","str","^rave","/str",true,{"x()":"activateBorder","exArgs":2},"pop","/ev","\n",{"->":".^.^.^.26"},null]}],"nop","\n","ev","void","/ev","->->",{"#f":1}],"npcEnd":["ev",false,{"x()":"pauseTutorial","exArgs":1},"pop","/ev","\n","ev",{"x()":"continueSinging"},"pop","/ev","\n","ev",{"f()":"restoreNPCsVolume"},"pop","/ev","\n","ev","str","^floral","/str",false,{"x()":"activateBorder","exArgs":2},"pop","/ev","\n","ev","str","^rave","/str",false,{"x()":"activateBorder","exArgs":2},"pop","/ev","\n","ev","void","/ev","->->",{"#f":1}],"global decl":["ev",0,{"VAR=":"world"},"/ev","end",null],"#f":1}],"listDefs":{}}